[{"model": "ayaloapp.myuser", "pk": 3, "fields": {"password": "pbkdf2_sha256$260000$AKH6cjBzkGcvvXPigfHGx7$BMHvsRspsSLcme4VanPzxOkzg5uPFotwJ56Ep/nxRsE=", "last_login": "2021-07-05T12:41:38.929Z", "is_superuser": "False", "first_name": "Valeria", "last_name": "Perry", "is_staff": "False", "is_active": True, "date_joined": "2021-07-05T12:41:38.929Z", "is_verified": True, "AccountType": "Leeser", "auth_provider": "null", "email": "Valeria.Perry@gmail.com", "cool_name": "Valeria123", "Gender": "Female", "Phone_number": "+2348045634221", "is_completely_verified": True, "groups": [], "user_permissions": []}}, {"model": "ayaloapp.myuser", "pk": 4, "fields": {"password": "pbkdf2_sha256$260000$AKH6cjBzkGcvvXPigfHGx7$BMHvsRspsSLcme4VanPzxOkzg5uPFotwJ56Ep/nxRsE=", "last_login": "2021-07-05T12:41:38.929Z", "is_superuser": "False", "first_name": "Lillian", "last_name": "Marcum", "is_staff": "False", "is_active": True, "date_joined": "2021-07-05T12:41:38.929Z", "is_verified": True, "AccountType": "Leeser", "auth_provider": "null", "email": "Lillian.Marcum@gmail.com", "cool_name": "Lillian123", "Gender": "Female", "Phone_number": "+2348045634221", "is_completely_verified": True, "groups": [], "user_permissions": []}}, {"model": "ayaloapp.myuser", "pk": 5, "fields": {"password": "pbkdf2_sha256$260000$AKH6cjBzkGcvvXPigfHGx7$BMHvsRspsSLcme4VanPzxOkzg5uPFotwJ56Ep/nxRsE=", "last_login": "2021-07-05T12:41:38.929Z", "is_superuser": "False", "first_name": "Gregory", "last_name": "Shinoda", "is_staff": "False", "is_active": True, "date_joined": "2021-07-05T12:41:38.929Z", "is_verified": True, "AccountType": "Leeser", "auth_provider": "null", "email": "Gregory.Shinoda@gmail.com", "cool_name": "Gregory123", "Gender": "Female", "Phone_number": "+2348045634221", "is_completely_verified": True, "groups": [], "user_permissions": []}}, {"model": "ayaloapp.myuser", "pk": 6, "fields": {"password": "pbkdf2_sha256$260000$AKH6cjBzkGcvvXPigfHGx7$BMHvsRspsSLcme4VanPzxOkzg5uPFotwJ56Ep/nxRsE=", "last_login": "2021-07-05T12:41:38.929Z", "is_superuser": "False", "first_name": "James", "last_name": "Rangel", "is_staff": "False", "is_active": True, "date_joined": "2021-07-05T12:41:38.929Z", "is_verified": True, "AccountType": "Leeser", "auth_provider": "null", "email": "James.Rangel@gmail.com", "cool_name": "James123", "Gender": "Female", "Phone_number": "+2348045634221", "is_completely_verified": True, "groups": [], "user_permissions": []}}, {"model": "ayaloapp.myuser", "pk": 7, "fields": {"password": "pbkdf2_sha256$260000$AKH6cjBzkGcvvXPigfHGx7$BMHvsRspsSLcme4VanPzxOkzg5uPFotwJ56Ep/nxRsE=", "last_login": "2021-07-05T12:41:38.929Z", "is_superuser": "False", "first_name": "Gene", "last_name": "Garcia", "is_staff": "False", "is_active": True, "date_joined": "2021-07-05T12:41:38.929Z", "is_verified": True, "AccountType": "Leeser", "auth_provider": "null", "email": "Gene.Garcia@gmail.com", "cool_name": "Gene123", "Gender": "Female", "Phone_number": "+2348045634221", "is_completely_verified": True, "groups": [], "user_permissions": []}}, {"model": "ayaloapp.myuser", "pk": 8, "fields": {"password": "pbkdf2_sha256$260000$AKH6cjBzkGcvvXPigfHGx7$BMHvsRspsSLcme4VanPzxOkzg5uPFotwJ56Ep/nxRsE=", "last_login": "2021-07-05T12:41:38.929Z", "is_superuser": "False", "first_name": "Luther", "last_name": "Moore", "is_staff": "False", "is_active": True, "date_joined": "2021-07-05T12:41:38.929Z", "is_verified": True, "AccountType": "Leeser", "auth_provider": "null", "email": "Luther.Moore@gmail.com", "cool_name": "Luther123", "Gender": "Female", "Phone_number": "+2348045634221", "is_completely_verified": True, "groups": [], "user_permissions": []}}, {"model": "ayaloapp.myuser", "pk": 9, "fields": {"password": "pbkdf2_sha256$260000$AKH6cjBzkGcvvXPigfHGx7$BMHvsRspsSLcme4VanPzxOkzg5uPFotwJ56Ep/nxRsE=", "last_login": "2021-07-05T12:41:38.929Z", "is_superuser": "False", "first_name": "Iluminada", "last_name": "Jennings", "is_staff": "False", "is_active": True, "date_joined": "2021-07-05T12:41:38.929Z", "is_verified": True, "AccountType": "Leeser", "auth_provider": "null", "email": "Iluminada.Jennings@gmail.com", "cool_name": "Iluminada123", "Gender": "Female", "Phone_number": "+2348045634221", "is_completely_verified": True, "groups": [], "user_permissions": []}}, {"model": "ayaloapp.myuser", "pk": 10, "fields": {"password": "pbkdf2_sha256$260000$AKH6cjBzkGcvvXPigfHGx7$BMHvsRspsSLcme4VanPzxOkzg5uPFotwJ56Ep/nxRsE=", "last_login": "2021-07-05T12:41:38.929Z", "is_superuser": "False", "first_name": "Juan", "last_name": "Schneider", "is_staff": "False", "is_active": True, "date_joined": "2021-07-05T12:41:38.929Z", "is_verified": True, "AccountType": "Leeser", "auth_provider": "null", "email": "Juan.Schneider@gmail.com", "cool_name": "Juan123", "Gender": "Female", "Phone_number": "+2348045634221", "is_completely_verified": True, "groups": [], "user_permissions": []}}, {"model": "ayaloapp.myuser", "pk": 11, "fields": {"password": "pbkdf2_sha256$260000$AKH6cjBzkGcvvXPigfHGx7$BMHvsRspsSLcme4VanPzxOkzg5uPFotwJ56Ep/nxRsE=", "last_login": "2021-07-05T12:41:38.929Z", "is_superuser": "False", "first_name": "Anthony", "last_name": "Villamar", "is_staff": "False", "is_active": True, "date_joined": "2021-07-05T12:41:38.929Z", "is_verified": True, "AccountType": "Leeser", "auth_provider": "null", "email": "Anthony.Villamar@gmail.com", "cool_name": "Anthony123", "Gender": "Female", "Phone_number": "+2348045634221", "is_completely_verified": True, "groups": [], "user_permissions": []}}, {"model": "ayaloapp.myuser", "pk": 12, "fields": {"password": "pbkdf2_sha256$260000$AKH6cjBzkGcvvXPigfHGx7$BMHvsRspsSLcme4VanPzxOkzg5uPFotwJ56Ep/nxRsE=", "last_login": "2021-07-05T12:41:38.929Z", "is_superuser": "False", "first_name": "Leslie", "last_name": "Clure", "is_staff": "False", "is_active": True, "date_joined": "2021-07-05T12:41:38.929Z", "is_verified": True, "AccountType": "Leeser", "auth_provider": "null", "email": "Leslie.Clure@gmail.com", "cool_name": "Leslie123", "Gender": "Female", "Phone_number": "+2348045634221", "is_completely_verified": True, "groups": [], "user_permissions": []}}, {"model": "ayaloapp.myuser", "pk": 13, "fields": {"password": "pbkdf2_sha256$260000$AKH6cjBzkGcvvXPigfHGx7$BMHvsRspsSLcme4VanPzxOkzg5uPFotwJ56Ep/nxRsE=", "last_login": "2021-07-05T12:41:38.929Z", "is_superuser": "False", "first_name": "Daniel", "last_name": "Cook", "is_staff": "False", "is_active": True, "date_joined": "2021-07-05T12:41:38.929Z", "is_verified": True, "AccountType": "Leeser", "auth_provider": "null", "email": "Daniel.Cook@gmail.com", "cool_name": "Daniel123", "Gender": "Female", "Phone_number": "+2348045634221", "is_completely_verified": True, "groups": [], "user_permissions": []}}, {"model": "ayaloapp.myuser", "pk": 14, "fields": {"password": "pbkdf2_sha256$260000$AKH6cjBzkGcvvXPigfHGx7$BMHvsRspsSLcme4VanPzxOkzg5uPFotwJ56Ep/nxRsE=", "last_login": "2021-07-05T12:41:38.929Z", "is_superuser": "False", "first_name": "Patricia", "last_name": "Prince", "is_staff": "False", "is_active": True, "date_joined": "2021-07-05T12:41:38.929Z", "is_verified": True, "AccountType": "Leeser", "auth_provider": "null", "email": "Patricia.Prince@gmail.com", "cool_name": "Patricia123", "Gender": "Female", "Phone_number": "+2348045634221", "is_completely_verified": True, "groups": [], "user_permissions": []}}, {"model": "ayaloapp.myuser", "pk": 15, "fields": {"password": "pbkdf2_sha256$260000$AKH6cjBzkGcvvXPigfHGx7$BMHvsRspsSLcme4VanPzxOkzg5uPFotwJ56Ep/nxRsE=", "last_login": "2021-07-05T12:41:38.929Z", "is_superuser": "False", "first_name": "Pamela", "last_name": "Williams", "is_staff": "False", "is_active": True, "date_joined": "2021-07-05T12:41:38.929Z", "is_verified": True, "AccountType": "Leeser", "auth_provider": "null", "email": "Pamela.Williams@gmail.com", "cool_name": "Pamela123", "Gender": "Female", "Phone_number": "+2348045634221", "is_completely_verified": True, "groups": [], "user_permissions": []}}, {"model": "ayaloapp.myuser", "pk": 16, "fields": {"password": "pbkdf2_sha256$260000$AKH6cjBzkGcvvXPigfHGx7$BMHvsRspsSLcme4VanPzxOkzg5uPFotwJ56Ep/nxRsE=", "last_login": "2021-07-05T12:41:38.929Z", "is_superuser": "False", "first_name": "Douglas", "last_name": "Carideo", "is_staff": "False", "is_active": True, "date_joined": "2021-07-05T12:41:38.929Z", "is_verified": True, "AccountType": "Leeser", "auth_provider": "null", "email": "Douglas.Carideo@gmail.com", "cool_name": "Douglas123", "Gender": "Female", "Phone_number": "+2348045634221", "is_completely_verified": True, "groups": [], "user_permissions": []}}, {"model": "ayaloapp.myuser", "pk": 17, "fields": {"password": "pbkdf2_sha256$260000$AKH6cjBzkGcvvXPigfHGx7$BMHvsRspsSLcme4VanPzxOkzg5uPFotwJ56Ep/nxRsE=", "last_login": "2021-07-05T12:41:38.929Z", "is_superuser": "False", "first_name": "Donna", "last_name": "Walton", "is_staff": "False", "is_active": True, "date_joined": "2021-07-05T12:41:38.929Z", "is_verified": True, "AccountType": "Leeser", "auth_provider": "null", "email": "Donna.Walton@gmail.com", "cool_name": "Donna123", "Gender": "Female", "Phone_number": "+2348045634221", "is_completely_verified": True, "groups": [], "user_permissions": []}}, {"model": "ayaloapp.myuser", "pk": 18, "fields": {"password": "pbkdf2_sha256$260000$AKH6cjBzkGcvvXPigfHGx7$BMHvsRspsSLcme4VanPzxOkzg5uPFotwJ56Ep/nxRsE=", "last_login": "2021-07-05T12:41:38.929Z", "is_superuser": "False", "first_name": "Stephen", "last_name": "Acosta", "is_staff": "False", "is_active": True, "date_joined": "2021-07-05T12:41:38.929Z", "is_verified": True, "AccountType": "Leeser", "auth_provider": "null", "email": "Stephen.Acosta@gmail.com", "cool_name": "Stephen123", "Gender": "Female", "Phone_number": "+2348045634221", "is_completely_verified": True, "groups": [], "user_permissions": []}}, {"model": "ayaloapp.myuser", "pk": 19, "fields": {"password": "pbkdf2_sha256$260000$AKH6cjBzkGcvvXPigfHGx7$BMHvsRspsSLcme4VanPzxOkzg5uPFotwJ56Ep/nxRsE=", "last_login": "2021-07-05T12:41:38.929Z", "is_superuser": "False", "first_name": "Victor", "last_name": "Landreth", "is_staff": "False", "is_active": True, "date_joined": "2021-07-05T12:41:38.929Z", "is_verified": True, "AccountType": "Leeser", "auth_provider": "null", "email": "Victor.Landreth@gmail.com", "cool_name": "Victor123", "Gender": "Female", "Phone_number": "+2348045634221", "is_completely_verified": True, "groups": [], "user_permissions": []}}, {"model": "ayaloapp.myuser", "pk": 20, "fields": {"password": "pbkdf2_sha256$260000$AKH6cjBzkGcvvXPigfHGx7$BMHvsRspsSLcme4VanPzxOkzg5uPFotwJ56Ep/nxRsE=", "last_login": "2021-07-05T12:41:38.929Z", "is_superuser": "False", "first_name": "Jody", "last_name": "Cassette", "is_staff": "False", "is_active": True, "date_joined": "2021-07-05T12:41:38.929Z", "is_verified": True, "AccountType": "Leeser", "auth_provider": "null", "email": "Jody.Cassette@gmail.com", "cool_name": "Jody123", "Gender": "Female", "Phone_number": "+2348045634221", "is_completely_verified": True, "groups": [], "user_permissions": []}}, {"model": "ayaloapp.myuser", "pk": 21, "fields": {"password": "pbkdf2_sha256$260000$AKH6cjBzkGcvvXPigfHGx7$BMHvsRspsSLcme4VanPzxOkzg5uPFotwJ56Ep/nxRsE=", "last_login": "2021-07-05T12:41:38.929Z", "is_superuser": "False", "first_name": "Victoria", "last_name": "Stein", "is_staff": "False", "is_active": True, "date_joined": "2021-07-05T12:41:38.929Z", "is_verified": True, "AccountType": "Leeser", "auth_provider": "null", "email": "Victoria.Stein@gmail.com", "cool_name": "Victoria123", "Gender": "Female", "Phone_number": "+2348045634221", "is_completely_verified": True, "groups": [], "user_permissions": []}}, {"model": "ayaloapp.myuser", "pk": 22, "fields": {"password": "pbkdf2_sha256$260000$AKH6cjBzkGcvvXPigfHGx7$BMHvsRspsSLcme4VanPzxOkzg5uPFotwJ56Ep/nxRsE=", "last_login": "2021-07-05T12:41:38.929Z", "is_superuser": "False", "first_name": "Michelle", "last_name": "Caul", "is_staff": "False", "is_active": True, "date_joined": "2021-07-05T12:41:38.929Z", "is_verified": True, "AccountType": "Leeser", "auth_provider": "null", "email": "Michelle.Caul@gmail.com", "cool_name": "Michelle123", "Gender": "Female", "Phone_number": "+2348045634221", "is_completely_verified": True, "groups": [], "user_permissions": []}}, {"model": "ayaloapp.myuser", "pk": 23, "fields": {"password": "pbkdf2_sha256$260000$AKH6cjBzkGcvvXPigfHGx7$BMHvsRspsSLcme4VanPzxOkzg5uPFotwJ56Ep/nxRsE=", "last_login": "2021-07-05T12:41:38.929Z", "is_superuser": "False", "first_name": "Helen", "last_name": "Campbell", "is_staff": "False", "is_active": True, "date_joined": "2021-07-05T12:41:38.929Z", "is_verified": True, "AccountType": "Leeser", "auth_provider": "null", "email": "Helen.Campbell@gmail.com", "cool_name": "Helen123", "Gender": "Female", "Phone_number": "+2348045634221", "is_completely_verified": True, "groups": [], "user_permissions": []}}, {"model": "ayaloapp.myuser", "pk": 24, "fields": {"password": "pbkdf2_sha256$260000$AKH6cjBzkGcvvXPigfHGx7$BMHvsRspsSLcme4VanPzxOkzg5uPFotwJ56Ep/nxRsE=", "last_login": "2021-07-05T12:41:38.929Z", "is_superuser": "False", "first_name": "Kimberly", "last_name": "Anderson", "is_staff": "False", "is_active": True, "date_joined": "2021-07-05T12:41:38.929Z", "is_verified": True, "AccountType": "Leeser", "auth_provider": "null", "email": "Kimberly.Anderson@gmail.com", "cool_name": "Kimberly123", "Gender": "Female", "Phone_number": "+2348045634221", "is_completely_verified": True, "groups": [], "user_permissions": []}}, {"model": "ayaloapp.myuser", "pk": 25, "fields": {"password": "pbkdf2_sha256$260000$AKH6cjBzkGcvvXPigfHGx7$BMHvsRspsSLcme4VanPzxOkzg5uPFotwJ56Ep/nxRsE=", "last_login": "2021-07-05T12:41:38.929Z", "is_superuser": "False", "first_name": "Ruthie", "last_name": "Eury", "is_staff": "False", "is_active": True, "date_joined": "2021-07-05T12:41:38.929Z", "is_verified": True, "AccountType": "Leeser", "auth_provider": "null", "email": "Ruthie.Eury@gmail.com", "cool_name": "Ruthie123", "Gender": "Female", "Phone_number": "+2348045634221", "is_completely_verified": True, "groups": [], "user_permissions": []}}, {"model": "ayaloapp.myuser", "pk": 26, "fields": {"password": "pbkdf2_sha256$260000$AKH6cjBzkGcvvXPigfHGx7$BMHvsRspsSLcme4VanPzxOkzg5uPFotwJ56Ep/nxRsE=", "last_login": "2021-07-05T12:41:38.929Z", "is_superuser": "False", "first_name": "Devin", "last_name": "Clark", "is_staff": "False", "is_active": True, "date_joined": "2021-07-05T12:41:38.929Z", "is_verified": True, "AccountType": "Leeser", "auth_provider": "null", "email": "Devin.Clark@gmail.com", "cool_name": "Devin123", "Gender": "Female", "Phone_number": "+2348045634221", "is_completely_verified": True, "groups": [], "user_permissions": []}}, {"model": "ayaloapp.myuser", "pk": 27, "fields": {"password": "pbkdf2_sha256$260000$AKH6cjBzkGcvvXPigfHGx7$BMHvsRspsSLcme4VanPzxOkzg5uPFotwJ56Ep/nxRsE=", "last_login": "2021-07-05T12:41:38.929Z", "is_superuser": "False", "first_name": "Jenelle", "last_name": "Whisler", "is_staff": "False", "is_active": True, "date_joined": "2021-07-05T12:41:38.929Z", "is_verified": True, "AccountType": "Leeser", "auth_provider": "null", "email": "Jenelle.Whisler@gmail.com", "cool_name": "Jenelle123", "Gender": "Female", "Phone_number": "+2348045634221", "is_completely_verified": True, "groups": [], "user_permissions": []}}, {"model": "ayaloapp.myuser", "pk": 28, "fields": {"password": "pbkdf2_sha256$260000$AKH6cjBzkGcvvXPigfHGx7$BMHvsRspsSLcme4VanPzxOkzg5uPFotwJ56Ep/nxRsE=", "last_login": "2021-07-05T12:41:38.929Z", "is_superuser": "False", "first_name": "David", "last_name": "Williams", "is_staff": "False", "is_active": True, "date_joined": "2021-07-05T12:41:38.929Z", "is_verified": True, "AccountType": "Leeser", "auth_provider": "null", "email": "David.Williams@gmail.com", "cool_name": "David123", "Gender": "Female", "Phone_number": "+2348045634221", "is_completely_verified": True, "groups": [], "user_permissions": []}}, {"model": "ayaloapp.myuser", "pk": 29, "fields": {"password": "pbkdf2_sha256$260000$AKH6cjBzkGcvvXPigfHGx7$BMHvsRspsSLcme4VanPzxOkzg5uPFotwJ56Ep/nxRsE=", "last_login": "2021-07-05T12:41:38.929Z", "is_superuser": "False", "first_name": "Wendy", "last_name": "Seale", "is_staff": "False", "is_active": True, "date_joined": "2021-07-05T12:41:38.929Z", "is_verified": True, "AccountType": "Leeser", "auth_provider": "null", "email": "Wendy.Seale@gmail.com", "cool_name": "Wendy123", "Gender": "Female", "Phone_number": "+2348045634221", "is_completely_verified": True, "groups": [], "user_permissions": []}}, {"model": "ayaloapp.myuser", "pk": 30, "fields": {"password": "pbkdf2_sha256$260000$AKH6cjBzkGcvvXPigfHGx7$BMHvsRspsSLcme4VanPzxOkzg5uPFotwJ56Ep/nxRsE=", "last_login": "2021-07-05T12:41:38.929Z", "is_superuser": "False", "first_name": "Christopher", "last_name": "Boender", "is_staff": "False", "is_active": True, "date_joined": "2021-07-05T12:41:38.929Z", "is_verified": True, "AccountType": "Leeser", "auth_provider": "null", "email": "Christopher.Boender@gmail.com", "cool_name": "Christopher123", "Gender": "Female", "Phone_number": "+2348045634221", "is_completely_verified": True, "groups": [], "user_permissions": []}}, {"model": "ayaloapp.myuser", "pk": 31, "fields": {"password": "pbkdf2_sha256$260000$AKH6cjBzkGcvvXPigfHGx7$BMHvsRspsSLcme4VanPzxOkzg5uPFotwJ56Ep/nxRsE=", "last_login": "2021-07-05T12:41:38.929Z", "is_superuser": "False", "first_name": "Andrew", "last_name": "Falco", "is_staff": "False", "is_active": True, "date_joined": "2021-07-05T12:41:38.929Z", "is_verified": True, "AccountType": "Leeser", "auth_provider": "null", "email": "Andrew.Falco@gmail.com", "cool_name": "Andrew123", "Gender": "Female", "Phone_number": "+2348045634221", "is_completely_verified": True, "groups": [], "user_permissions": []}}, {"model": "ayaloapp.myuser", "pk": 32, "fields": {"password": "pbkdf2_sha256$260000$AKH6cjBzkGcvvXPigfHGx7$BMHvsRspsSLcme4VanPzxOkzg5uPFotwJ56Ep/nxRsE=", "last_login": "2021-07-05T12:41:38.929Z", "is_superuser": "False", "first_name": "Patricia", "last_name": "Harwell", "is_staff": "False", "is_active": True, "date_joined": "2021-07-05T12:41:38.929Z", "is_verified": True, "AccountType": "Leeser", "auth_provider": "null", "email": "Patricia.Harwell@gmail.com", "cool_name": "Patricia123", "Gender": "Female", "Phone_number": "+2348045634221", "is_completely_verified": True, "groups": [], "user_permissions": []}}, {"model": "ayaloapp.myuser", "pk": 33, "fields": {"password": "pbkdf2_sha256$260000$AKH6cjBzkGcvvXPigfHGx7$BMHvsRspsSLcme4VanPzxOkzg5uPFotwJ56Ep/nxRsE=", "last_login": "2021-07-05T12:41:38.929Z", "is_superuser": "False", "first_name": "Diane", "last_name": "Gomez", "is_staff": "False", "is_active": True, "date_joined": "2021-07-05T12:41:38.929Z", "is_verified": True, "AccountType": "Leeser", "auth_provider": "null", "email": "Diane.Gomez@gmail.com", "cool_name": "Diane123", "Gender": "Female", "Phone_number": "+2348045634221", "is_completely_verified": True, "groups": [], "user_permissions": []}}, {"model": "ayaloapp.myuser", "pk": 34, "fields": {"password": "pbkdf2_sha256$260000$AKH6cjBzkGcvvXPigfHGx7$BMHvsRspsSLcme4VanPzxOkzg5uPFotwJ56Ep/nxRsE=", "last_login": "2021-07-05T12:41:38.929Z", "is_superuser": "False", "first_name": "Laura", "last_name": "Hill", "is_staff": "False", "is_active": True, "date_joined": "2021-07-05T12:41:38.929Z", "is_verified": True, "AccountType": "Leeser", "auth_provider": "null", "email": "Laura.Hill@gmail.com", "cool_name": "Laura123", "Gender": "Female", "Phone_number": "+2348045634221", "is_completely_verified": True, "groups": [], "user_permissions": []}}, {"model": "ayaloapp.myuser", "pk": 35, "fields": {"password": "pbkdf2_sha256$260000$AKH6cjBzkGcvvXPigfHGx7$BMHvsRspsSLcme4VanPzxOkzg5uPFotwJ56Ep/nxRsE=", "last_login": "2021-07-05T12:41:38.929Z", "is_superuser": "False", "first_name": "Evelyn", "last_name": "Crossley", "is_staff": "False", "is_active": True, "date_joined": "2021-07-05T12:41:38.929Z", "is_verified": True, "AccountType": "Leeser", "auth_provider": "null", "email": "Evelyn.Crossley@gmail.com", "cool_name": "Evelyn123", "Gender": "Female", "Phone_number": "+2348045634221", "is_completely_verified": True, "groups": [], "user_permissions": []}}, {"model": "ayaloapp.myuser", "pk": 36, "fields": {"password": "pbkdf2_sha256$260000$AKH6cjBzkGcvvXPigfHGx7$BMHvsRspsSLcme4VanPzxOkzg5uPFotwJ56Ep/nxRsE=", "last_login": "2021-07-05T12:41:38.929Z", "is_superuser": "False", "first_name": "Theresa", "last_name": "Mullet", "is_staff": "False", "is_active": True, "date_joined": "2021-07-05T12:41:38.929Z", "is_verified": True, "AccountType": "Leeser", "auth_provider": "null", "email": "Theresa.Mullet@gmail.com", "cool_name": "Theresa123", "Gender": "Female", "Phone_number": "+2348045634221", "is_completely_verified": True, "groups": [], "user_permissions": []}}, {"model": "ayaloapp.myuser", "pk": 37, "fields": {"password": "pbkdf2_sha256$260000$AKH6cjBzkGcvvXPigfHGx7$BMHvsRspsSLcme4VanPzxOkzg5uPFotwJ56Ep/nxRsE=", "last_login": "2021-07-05T12:41:38.929Z", "is_superuser": "False", "first_name": "Mary", "last_name": "Boyer", "is_staff": "False", "is_active": True, "date_joined": "2021-07-05T12:41:38.929Z", "is_verified": True, "AccountType": "Leeser", "auth_provider": "null", "email": "Mary.Boyer@gmail.com", "cool_name": "Mary123", "Gender": "Female", "Phone_number": "+2348045634221", "is_completely_verified": True, "groups": [], "user_permissions": []}}, {"model": "ayaloapp.myuser", "pk": 38, "fields": {"password": "pbkdf2_sha256$260000$AKH6cjBzkGcvvXPigfHGx7$BMHvsRspsSLcme4VanPzxOkzg5uPFotwJ56Ep/nxRsE=", "last_login": "2021-07-05T12:41:38.929Z", "is_superuser": "False", "first_name": "Russell", "last_name": "Haygood", "is_staff": "False", "is_active": True, "date_joined": "2021-07-05T12:41:38.929Z", "is_verified": True, "AccountType": "Leeser", "auth_provider": "null", "email": "Russell.Haygood@gmail.com", "cool_name": "Russell123", "Gender": "Female", "Phone_number": "+2348045634221", "is_completely_verified": True, "groups": [], "user_permissions": []}}, {"model": "ayaloapp.myuser", "pk": 39, "fields": {"password": "pbkdf2_sha256$260000$AKH6cjBzkGcvvXPigfHGx7$BMHvsRspsSLcme4VanPzxOkzg5uPFotwJ56Ep/nxRsE=", "last_login": "2021-07-05T12:41:38.929Z", "is_superuser": "False", "first_name": "Sonia", "last_name": "Wade", "is_staff": "False", "is_active": True, "date_joined": "2021-07-05T12:41:38.929Z", "is_verified": True, "AccountType": "Leeser", "auth_provider": "null", "email": "Sonia.Wade@gmail.com", "cool_name": "Sonia123", "Gender": "Female", "Phone_number": "+2348045634221", "is_completely_verified": True, "groups": [], "user_permissions": []}}, {"model": "ayaloapp.myuser", "pk": 40, "fields": {"password": "pbkdf2_sha256$260000$AKH6cjBzkGcvvXPigfHGx7$BMHvsRspsSLcme4VanPzxOkzg5uPFotwJ56Ep/nxRsE=", "last_login": "2021-07-05T12:41:38.929Z", "is_superuser": "False", "first_name": "Patsy", "last_name": "Willis", "is_staff": "False", "is_active": True, "date_joined": "2021-07-05T12:41:38.929Z", "is_verified": True, "AccountType": "Leeser", "auth_provider": "null", "email": "Patsy.Willis@gmail.com", "cool_name": "Patsy123", "Gender": "Female", "Phone_number": "+2348045634221", "is_completely_verified": True, "groups": [], "user_permissions": []}}, {"model": "ayaloapp.myuser", "pk": 41, "fields": {"password": "pbkdf2_sha256$260000$AKH6cjBzkGcvvXPigfHGx7$BMHvsRspsSLcme4VanPzxOkzg5uPFotwJ56Ep/nxRsE=", "last_login": "2021-07-05T12:41:38.929Z", "is_superuser": "False", "first_name": "Stacy", "last_name": "Calderon", "is_staff": "False", "is_active": True, "date_joined": "2021-07-05T12:41:38.929Z", "is_verified": True, "AccountType": "Leeser", "auth_provider": "null", "email": "Stacy.Calderon@gmail.com", "cool_name": "Stacy123", "Gender": "Female", "Phone_number": "+2348045634221", "is_completely_verified": True, "groups": [], "user_permissions": []}}, {"model": "ayaloapp.myuser", "pk": 42, "fields": {"password": "pbkdf2_sha256$260000$AKH6cjBzkGcvvXPigfHGx7$BMHvsRspsSLcme4VanPzxOkzg5uPFotwJ56Ep/nxRsE=", "last_login": "2021-07-05T12:41:38.929Z", "is_superuser": "False", "first_name": "Darcy", "last_name": "Carter", "is_staff": "False", "is_active": True, "date_joined": "2021-07-05T12:41:38.929Z", "is_verified": True, "AccountType": "Leeser", "auth_provider": "null", "email": "Darcy.Carter@gmail.com", "cool_name": "Darcy123", "Gender": "Female", "Phone_number": "+2348045634221", "is_completely_verified": True, "groups": [], "user_permissions": []}}]